{"TableName":"ItemsTable","DataPath":"Data","Columns":["ItemName","ItemNameAlias","ItemCode","Rate","GstPercentage","hsn"],"ColumnsWithSchema":[{"field":"ItemName","title":"ItemName","unique":true,"type":"text","isInput":true,"isAutoFocus":true,"WidthOptions":{"inPx":200}},{"field":"ItemNameAlias","title":"ItemNameAlias","unique":true,"type":"text","isInput":true,"isAutoFocus":true,"WidthOptions":{"inPx":200}},{"field":"ItemCode","title":"ItemCode","unique":true,"type":"text","isInput":true,"WidthOptions":{"inPx":200}},{"field":"Rate","title":"Rate","unique":false,"type":"number","isNumber":true},{"field":"GstPercentage","title":"Gst %","unique":false,"type":"number","isNumber":true,"defaultvalue":18},{"field":"hsn","title":"hsn","unique":false,"type":"number","isNumber":true}],"DefaultObjectToInsert":{"Simple":{"ItemName":"om namo venkateswara","ItemCode":"1","ItemNameAlias":"","Rate":616,"GstPercentage":18,"hsn":8714,"pk":65}}}